pynqutils/__init__.py
pynqutils/version.txt
pynqutils/build_utils/__init__.py
pynqutils/build_utils/bdc_meta.py
pynqutils/build_utils/boardstore.py
pynqutils/build_utils/pynq_bdc_patcher.py
pynqutils/build_utils/xsa_parser.py
pynqutils/runtime/__init__.py
pynqutils/runtime/detect_devices.py
pynqutils/runtime/logging.py
pynqutils/runtime/repr_dict.py
pynqutils/runtime/run_notebook.py
pynqutils/setup_utils/__init__.py
pynqutils/setup_utils/deliver_notebooks.py
pynqutils/setup_utils/download_overlays.py
pynqutils/setup_utils/extend_package.py
pynqutils/setup_utils/extension_manager.py
pynqutils/setup_utils/get_board.py
pynqutils/setup_utils/get_platform.py
pynqutils/setup_utils/parse_version_number.py
pynqutils-0.1.1.dist-info/LICENSE
pynqutils-0.1.1.dist-info/METADATA
pynqutils-0.1.1.dist-info/WHEEL
pynqutils-0.1.1.dist-info/top_level.txt
pynqutils-0.1.1.dist-info/RECORD
