Metadata-Version: 2.1
Name: pynqutils
Version: 0.1.1
Summary: Utilities for PYNQ
Home-page: https://github.com/Xilinx/PYNQ-Utils
Author: pynq
Author-email: pynq_support@xilinx.com
License: BSD 3-Clause
Platform: UNKNOWN
Requires-Python: >=3.5.2
Requires-Dist: cffi
Requires-Dist: numpy
Requires-Dist: pynqmetadata (>=0.0.1)
Requires-Dist: python-magic (>=0.4.25)
Requires-Dist: setuptools (>=24.2.0)
Requires-Dist: tqdm
